setup.py
mixpanel/__init__.py
mixpanel/consumer_tornado.py
mixpanel_py3.egg-info/PKG-INFO
mixpanel_py3.egg-info/SOURCES.txt
mixpanel_py3.egg-info/dependency_links.txt
mixpanel_py3.egg-info/top_level.txt