Metadata-Version: 1.1
Name: mixpanel-py3
Version: 3.0.2
Summary: Mixpanel library for Python3.3
Home-page: https://github.com/MyGGaN/mixpanel-python
Author: Fredrik Svensson
Author-email: shootoneshot@hotmail.com
License: UNKNOWN
Platform: UNKNOWN
Classifier: License :: OSI Approved :: Apache Software License
Classifier: Operating System :: OS Independent
Classifier: Programming Language :: Python :: 3
Classifier: Programming Language :: Python :: 3.3
Classifier: Programming Language :: Python :: 3.4
